surveillance_bot/__init__.py
surveillance_bot/bot.py
surveillance_bot/bot_config.py
surveillance_bot/camera.py
surveillance_bot/main.py
surveillance_bot-1.1.1.dist-info/LICENSE.txt
surveillance_bot-1.1.1.dist-info/METADATA
surveillance_bot-1.1.1.dist-info/WHEEL
surveillance_bot-1.1.1.dist-info/entry_points.txt
surveillance_bot-1.1.1.dist-info/top_level.txt
surveillance_bot-1.1.1.dist-info/RECORD
