Metadata-Version: 2.1
Name: surveillance-bot
Version: 1.1.1
Summary: Basic video surveillance system controlled through a telegram bot.
Home-page: https://github.com/pchinea/telegram-surveillance-bot
Author: Pablo Chinea
Author-email: khertz@gmail.com
License: GPL v3
Platform: UNKNOWN
Classifier: Development Status :: 5 - Production/Stable
Classifier: Environment :: Console
Classifier: License :: OSI Approved :: GNU General Public License v3 (GPLv3)
Classifier: Operating System :: OS Independent
Classifier: Programming Language :: Python
Classifier: Programming Language :: Python :: 3 :: Only
Classifier: Programming Language :: Python :: 3.6
Classifier: Programming Language :: Python :: 3.7
Classifier: Programming Language :: Python :: 3.8
Classifier: Programming Language :: Python :: 3.9
Classifier: Topic :: Communications :: Chat
Classifier: Topic :: Internet
Classifier: Topic :: Multimedia :: Graphics :: Capture :: Digital Camera
Classifier: Topic :: Multimedia :: Video :: Capture
Classifier: Topic :: Security
Classifier: Topic :: Utilities
Requires-Python: >=3.6, <3.10
Requires-Dist: opencv-python-headless (<5,>=4)
Requires-Dist: python-telegram-bot (<14,>=13)
